trackip.py
trackip-1.0.0.dist-info/LICENSE
trackip-1.0.0.dist-info/METADATA
trackip-1.0.0.dist-info/WHEEL
trackip-1.0.0.dist-info/entry_points.txt
trackip-1.0.0.dist-info/top_level.txt
trackip-1.0.0.dist-info/RECORD
