Metadata-Version: 2.2
Name: trackip
Version: 1.0.0
Summary: A CLI tool to track any IP address and get detailed info. 🌍
Home-page: https://github.com/nayandas69/trackip
Author: Nayan Das
Author-email: nayanchandradas@hotmail.com
License: Apache-2.0
Project-URL: Bug Tracker, https://github.com/nayandas69/trackip/issues
Project-URL: Documentation, https://github.com/nayandas69/trackip#readme
Project-URL: Source Code, https://github.com/nayandas69/trackip
Keywords: IP tracker,CLI tool,IP geolocation,networking,geolocation,IP lookup,IP address info,public IP checker,CLI geolocation,track IP
Classifier: Development Status :: 5 - Production/Stable
Classifier: Intended Audience :: Developers
Classifier: Topic :: Utilities
Classifier: Programming Language :: Python :: 3
Classifier: License :: OSI Approved :: Apache Software License
Classifier: Operating System :: OS Independent
Requires-Python: >=3.6
License-File: LICENSE
Requires-Dist: requests>=2.25.1
Requires-Dist: colorama>=0.4.4
Dynamic: author
Dynamic: author-email
Dynamic: classifier
Dynamic: description
Dynamic: description-content-type
Dynamic: home-page
Dynamic: keywords
Dynamic: license
Dynamic: project-url
Dynamic: requires-dist
Dynamic: requires-python
Dynamic: summary
